mutation_profile/__init__.py
mutation_profile/__main__.py
mutation_profile/mutation_profile.py
mutation_profile-0.2.1.dist-info/entry_points.txt
mutation_profile-0.2.1.dist-info/LICENSE
mutation_profile-0.2.1.dist-info/WHEEL
mutation_profile-0.2.1.dist-info/METADATA
mutation_profile-0.2.1.dist-info/RECORD
