Metadata-Version: 2.1
Name: mutation-profile
Version: 0.2.1
Summary: A bioinformatics solution to determine SNP flanking sequences and mutation profile
Home-page: https://github.com/insapathogenomics/mutation_profile
License: GPL-3.0-only
Author: Veronica Mixao
Author-email: vmixao@gmail.com
Requires-Python: >=3.8,<4.0
Classifier: License :: OSI Approved :: GNU General Public License v3 (GPLv3)
Classifier: Programming Language :: Python :: 3
Classifier: Programming Language :: Python :: 3.10
Classifier: Programming Language :: Python :: 3.8
Classifier: Programming Language :: Python :: 3.9
Requires-Dist: biopython (>=1.80,<2.0)
Requires-Dist: pandas (>=1.4.3,<2.0.0)
Requires-Dist: requests (>=2.31.0,<3.0.0)
Requires-Dist: textwrap3 (>=0.9.2,<0.10.0)
Project-URL: Repository, https://github.com/insapathogenomics/mutation_profile
